PIT_APP/__init__.py
PIT_APP/asgi.py
PIT_APP/routing.py
PIT_APP/settings.py
PIT_APP/urls.py
PIT_APP/wsgi.py
PIT_APP/PIT_APP/__init__.py
PIT_APP/PIT_APP/asgi.py
PIT_APP/PIT_APP/routing.py
PIT_APP/PIT_APP/settings.py
PIT_APP/PIT_APP/urls.py
PIT_APP/PIT_APP/views.py
PIT_APP/PIT_APP/wsgi.py
PIT_APP/static/bootstrap.min.css
PIT_APP/static/bootstrap.min.js
PIT_APP/static/favicon.ico
PIT_APP/static/jquery.min.js
PIT_APP/static/popper.min.js
PIT_APP/static/CACHE/manifest.json
PIT_APP/static/CACHE/manifest.json.gz
PIT_APP/static/CACHE/css/output.680af6669abc.css
PIT_APP/static/CACHE/js/output.0fc6fac7fd55.js
PIT_APP/static/admin/css/autocomplete.css
PIT_APP/static/admin/css/base.css
PIT_APP/static/admin/css/changelists.css
PIT_APP/static/admin/css/dashboard.css
PIT_APP/static/admin/css/fonts.css
PIT_APP/static/admin/css/forms.css
PIT_APP/static/admin/css/login.css
PIT_APP/static/admin/css/nav_sidebar.css
PIT_APP/static/admin/css/responsive.css
PIT_APP/static/admin/css/responsive_rtl.css
PIT_APP/static/admin/css/rtl.css
PIT_APP/static/admin/css/widgets.css
PIT_APP/static/admin/css/vendor/select2/LICENSE-SELECT2.md
PIT_APP/static/admin/css/vendor/select2/select2.css
PIT_APP/static/admin/css/vendor/select2/select2.min.css
PIT_APP/static/admin/fonts/LICENSE.txt
PIT_APP/static/admin/fonts/README.txt
PIT_APP/static/admin/fonts/Roboto-Bold-webfont.woff
PIT_APP/static/admin/fonts/Roboto-Light-webfont.woff
PIT_APP/static/admin/fonts/Roboto-Regular-webfont.woff
PIT_APP/static/admin/img/LICENSE
PIT_APP/static/admin/img/README.txt
PIT_APP/static/admin/img/calendar-icons.svg
PIT_APP/static/admin/img/icon-addlink.svg
PIT_APP/static/admin/img/icon-alert.svg
PIT_APP/static/admin/img/icon-calendar.svg
PIT_APP/static/admin/img/icon-changelink.svg
PIT_APP/static/admin/img/icon-clock.svg
PIT_APP/static/admin/img/icon-deletelink.svg
PIT_APP/static/admin/img/icon-no.svg
PIT_APP/static/admin/img/icon-unknown-alt.svg
PIT_APP/static/admin/img/icon-unknown.svg
django_pit_survey-1.0.0.dist-info/METADATA
django_pit_survey-1.0.0.dist-info/WHEEL
django_pit_survey-1.0.0.dist-info/entry_points.txt
django_pit_survey-1.0.0.dist-info/top_level.txt
django_pit_survey-1.0.0.dist-info/RECORD
